AUTHORS.txt
CHANGELOG.txt
COPYING.txt
MANIFEST.in
README.md
setup.py
django_online_counter.egg-info/PKG-INFO
django_online_counter.egg-info/SOURCES.txt
django_online_counter.egg-info/dependency_links.txt
django_online_counter.egg-info/top_level.txt
onlinecounter/__init__.py
onlinecounter/admin.py
onlinecounter/middleware.py
onlinecounter/models.py
onlinecounter/views.py
onlinecounter/demo/__init__.py
onlinecounter/demo/manage.py
onlinecounter/demo/settings.py
onlinecounter/demo/urls.py