Metadata-Version: 1.0
Name: django-online-counter
Version: 1.0
Summary: Django online visitor counter
Home-page: http://www.metehan.us/
Author: Metehan Özbek
Author-email: metehan[at]metehan.us
License: GPL v3
Keywords: django,online counter
Platform: UNKNOWN
Classifier: License :: OSI Approved :: GNU Affero General Public License v3
Classifier: Environment :: Web Environment
Classifier: Framework :: Django
